{
		"id": "peter-utton-website-v2", 
		"name": "Peter Utton Website (v2)",
		"category": "Static",
		"date": "2012-13",
		"tech": [
			{"tag": "HTML, CSS"},
			{"tag": "jQuery"},
			{"tag": "Powa CMS"}

		],
		"deliverTitle": "What we delivered",
		"deliverItems": [
			{"item": "Branding for the web"},
			{"item": "New logo"},
			{"item": "Showcase/informative website"}
		],
		"how": {
			"title": "My involvement",
			"thoughts": "<p>I worked very closely with Peter during the design - we turned Peter's hand crafted art into web-safe branding and material.</p>"
		},
		"liveUrl": "http://peterutton.com"
}